Workbook

Sheet README
B2: FRAZIYM — One Product, Many Tools | Opportunity Database
B4: What this file is
B5: Scored opportunity database for the FRAZIYM ecosystem: ONE subscription product that bundles 240+ micro-tools (including long-tail tools used <=1x/month), priced per user plan — never per-tool, never underpriced. Built from 7 research streams (2026-09-02) with URL-sourced evidence.
B7: The 247 rows
B8: 103 research-locked rows (from data-repair DR-*, e-commerce EC-*, devtools DV-*, weird-gold WG-* streams) + 144 long-tail catalog rows (GT-*, pattern-inherited E3, each pointing to its research parent). Every row = one tool/feature candidate for the platform.
B10: Evidence legend
B11: E1 = direct community complaint/thread found (highest confidence). E2 = verified product/pricing/docs fact. E3 = pattern-inferred hypothesis — validate before building. 79 E1 / 15 E2 / 153 E3.
B13: Scoring model (10 dims)
B14: Demand 20% | Pain 15% | Frequency 10% | Automation 15% | Monetization 10% | Distribution 10% | Competition 5% (high=low rivalry) | Infra-econ 5% | Ecosystem 5% | Defensibility 5%. Composite = weighted sum, 0-10.
B16: Platform roles
B17: HOOK = free acquisition surface (SEO traffic). GLUE = keeps users returning (daily utilities). PRO = paywall-worthy professional features. LTV = flagship high-value tools that justify the subscription on their own (e.g., bank-statement PDF->CSV replaces $49.95/mo DocuClipper).
B19: Tier fit
... B31: Prepared 2026-09-03 | Full sources: research/*.md + download/FRAZIYM_Research_Export_Phase1.md | Currency: USD

Sheet Opportunities
B2: All 247 Scored Opportunities (filterable)
B4: Rank | C4: ID | D4: Tool / Opportunity | E4: Zone | F4: Cluster | G4: Evidence | H4: Composite | I4: Demand | J4: Pain | K4: Freq | L4: Automation | M4: Monetize | N4: Distrib | O4: Comp* | P4: Infra | Q4: Eco | R4: Defen | S4: Role | T4: Tier | U4: Effort h | V4: Maint min/wk | W4: AI | X4: SEO query / parent | Y4: Problem (abridged)
B5: 1 | C5: DR-C3 | D5: Adobe Acrobat's subscription-only pricing outrages buyers who need occasional PDF editing/merging/forms. | E5: Data & Repair | F5: Data & File Repair | G5: E1 | H5: 8.2 | I5: 9 | J5: 7 | K5: 9 | L5: 10 | M5: 6 | N5: 9 | O5: 4.5 | P5: 9.5 | Q5: 9 | R5: 6 | S5: HOOK | T5: FREE | U5: 10 | V5: 10 | W5: N | Y5: Adobe Acrobat's subscription-only pricing outrages buyers who need occasional PDF editing/merging/forms.
B6: 2 | C6: DR-F1 | D6: Bookkeepers cannot import bank transactions from PDF statements — QuickBooks Online users beg for PDF→CSV/Q... | E6: Data & Repair | F6: Data & File Repair | G6: E1 | H6: 8.03 | I6: 8.5 | J6: 9.5 | K6: 7 | L6: 8.5 | M6: 9 | N6: 7 | O6: 6 | P6: 6.5 | Q6: 8 | R6: 6 | S6: LTV | T6: PRO | U6: 40 | V6: 45 | W6: Y | Y6: Bookkeepers cannot import bank transactions from PDF statements — QuickBooks Online users beg for PDF→CSV/QBO conversion and are desperate when banks close online history.
B7: 3 | C7: GT-PDF-extract-DR-C2 | D7: PDF Table Extractor to CSV (text-layer) | E7: Data & Repair | F7: Data & File Repair | G7: E3 | H7: 7.75 | I7: 9 | J7: 8 | K7: 5 | L7: 9 | M7: 7 | N7: 9 | O7: 6 | P7: 7 | Q7: 8 | R7: 5 | S7: LTV | T7: PRO | U7: 40 | V7: 10 | W7: N | X7: extract tables from pdf to csv | Y7: Long-tail tool instance: PDF Table Extractor to CSV (text-layer). Pattern-inherited pain evidence from DR-C2 cluster; ships as part of the mega-toolbox catalog (<=1 use/month tools included by directive).
B8: 4 | C8: DR-D2 | D8: One conversion job requires stitching 3-5 different single-purpose sites/tools; users lose track and hit ea... | E8: Data & Repair | F8: Data & File Repair | G8: E1 | H8: 7.67 | I8: 9 | J8: 8 | K8: 7 | L8: 8.5 | M8: 5 | N8: 8 | O8: 3.5 | P8: 9.5 | Q8: 10 | R8: 5 | S8: HOOK | T8: FREE | U8: 12 | V8: 10 | W8: N | Y8: One conversion job requires stitching 3-5 different single-purpose sites/tools; users lose track and hit each tool's free caps.
B9: 5 | C9: DR-B2 | D9: Multi-hundred-MB/GB JSON & JSONL files crash or freeze editors (VS Code 5MB JSON mode limit; 700MB jsonline... | E9: Data & Repair | F9: Data & File Repair | G9: E1 | H9: 7.62 | I9: 9 | J9: 8.5 | K9: 7 | L9: 8.5 | M9: 5 | N9: 9 | O9: 3.5 | P9: 9.5 | Q9: 4.5 | R9: 6 | S9: HOOK | T9: FREE | U9: 12 | V9: 10 | W9: N | Y9: Multi-hundred-MB/GB JSON & JSONL files crash or freeze editors (VS Code 5MB JSON mode limit; 700MB jsonlines crashes VS Code).
B10: 6 | C10: DR-H1 | D10: SMBs and individuals still spend hours monthly on manual invoice/receipt data entry and want any automation... | E10: Data & Repair | F10: Data & File Repair | G10: E1 | H10: 7.6 | I10: 8 | J10: 8 | K10: 9 | L10: 8.5 | M10: 7.5 | N10: 7 | O10: 6.5 | P10: 6 | Q10: 7 | R10: 4 | S10: LTV | T10: MAX | U10: 40 | V10: 45 | W10: Y | Y10: SMBs and individuals still spend hours monthly on manual invoice/receipt data entry and want any automation that actually works.
B11: 7 | C11: WG-G4 | D11: Hallucinated citations — verifying AI-generated references | E11: Education & Weird Gold | F11: Weird Gold / Education | G11: E1 | H11: 7.6 | I11: 8 | J11: 9.5 | K11: 6 | L11: 6.5 | M11: 7.5 | N11: 8 | O11: 9 | P11: 6 | Q11: 7 | R11: 7 | S11: LTV | T11: MAX | U11: 36 | V11: 30 | W11: N | Y11: Nature-linked analysis: "Tens of thousands of publications from 2025 might include invalid references generated by AI" (r/technology thread: https://www.reddit.com/r/technology/comments/1sd0khs/); study: ChatGPT false-citation rates 6%–60% by domain (https://w
B12: 8 | C12: GT-CSV-split-DR-B2 | D12: CSV Splitter (rows / file size) | E12: Data & Repair | F12: Data & File Repair | G12: E3 | H12: 7.6 | I12: 8 | J12: 8 | K12: 5 | L12: 10 | M12: 6 | N12: 9 | O12: 5 | P12: 10 | Q12: 7 | R12: 4 | S12: PRO | T12: PRO | U12: 8 | V12: 10 | W12: N | X12: split large csv files | Y12: Long-tail tool instance: CSV Splitter (rows / file size). Pattern-inherited pain evidence from DR-B2 cluster; ships as part of the mega-toolbox catalog (<=1 use/month tools included by directive).
B13: 9 | C13: GT-CSV-excel-DR-A2 | D13: Leading-Zero & Date Guard (CSV open protector) | E13: Data & Repair | F13: Data & File Repair | G13: E3 | H13: 7.6 | I13: 8 | J13: 8 | K13: 6 | L13: 10 | M13: 5 | N13: 9 | O13: 5 | P13: 10 | Q13: 7 | R13: 4 | S13: PRO | T13: PRO | U13: 10 | V13: 10 | W13: N | X13: excel removes leading zeros fix | Y13: Long-tail tool instance: Leading-Zero & Date Guard (CSV open protector). Pattern-inherited pain evidence from DR-A2 cluster; ships as part of the mega-toolbox catalog (<=1 use/month tools included by directive).
B14: 10 | C14: EC-C21 | D14: Manually matching bank/UPI payments to invoices/orders — sellers literally work out "which combinations of ... | E14: E-commerce & SMB | F14: E-commerce & SMB Ops | G14: E1 | H14: 7.58 | I14: 6.5 | J14: 9 | K14: 7 | L14: 8.5 | M14: 8 | N14: 7 | O14: 9 | P14: 6 | Q14: 8 | R14: 6 | S14: LTV | T14: PRO | U14: 12 | V14: 10 | W14: N | Y14: Manually matching bank/UPI payments to invoices/orders — sellers literally work out "which combinations of invoice amounts add up to each payment amount" on weekends; UPI/direct-transfer payments arrive with no references.
B15: 11 | C15: DV-B1 | D15: JSON viewers/editors crash or freeze on large (100MB–1GB+) JSON files, so devs fall back to command-line jq... | E15: DevTools & Data | F15: Developer Tools | G15: E1 | H15: 7.58 | I15: 7.5 | J15: 7 | K15: 7 | L15: 10 | M15: 6.5 | N15: 8 | O15: 6 | P15: 10 | Q15: 5.5 | R15: 6 | S15: PRO | T15: PRO | U15: 10 | V15: 10 | W15: N | X15: strong free-tool wedge with clear upgrade path (browser WASM = differentiator "file never leaves your machine"). | Y15: JSON viewers/editors crash or freeze on large (100MB–1GB+) JSON files, so devs fall back to command-line jq or buy specialized viewers.
B16: 12 | C16: DR-A2 | D16: CSVs open with all data in one column or split wrongly because the delimiter is comma vs semicolon (Europea... | E16: Data & Repair | F16: Data & File Repair | G16: E1 | H16: 7.55 | I16: 9 | J16: 8 | K16: 9 | L16: 8.5 | M16: 5 | N16: 9 | O16: 3.5 | P16: 7.5 | Q16: 4.5 | R16: 4 | S16: HOOK | T16: FREE | U16: 12 | V16: 10 | W16: N | Y16: CSVs open with all data in one column or split wrongly because the delimiter is comma vs semicolon (European locale) or SEP= line missing.
B17: 13 | C17: EC-C28 | D17: (Developing-market angle, partially inferred) Bangladesh/South-Asia micro-sellers keep records in manual kh... | E17: E-commerce & SMB | F17: E-commerce & SMB Ops | G17: E2 | H17: 7.55 | I17: 8 | J17: 7 | K17: 9 | L17: 8.5 | M17: 6 | N17: 8 | O17: 8.5 | P17: 7.5 | Q17: 4.5 | R17: 6 | S17: HOOK | T17: FREE | U17: 12 | V17: 10 | W17: N | Y17: (Developing-market angle, partially inferred) Bangladesh/South-Asia micro-sellers keep records in manual khata notebooks or Excel; local-language/local-format accounting software is thin; bKash/wallet payment trails live in SMS and screenshots, not ledgers.
B18: 14 | C18: EC-C29 | D18: WhatsApp-order chaos: sellers take 20–30 orders/day as chat messages; tracking in notebook/Excel/memory; no... | E18: E-commerce & SMB | F18: E-commerce & SMB Ops | G18: E1 | H18: 7.55 | I18: 7.5 | J18: 8.5 | K18: 9 | L18: 8.5 | M18: 7 | N18: 5 | O18: 8.5 | P18: 7.5 | Q18: 8 | R18: 4 | S18: LTV | T18: PRO | U18: 12 | V18: 10 | W18: N | Y18: WhatsApp-order chaos: sellers take 20–30 orders/day as chat messages; tracking in notebook/Excel/memory; no order numbers, missed orders, no payment status.
B19: 15 | C19: WG-G5 | D19: AI-detector false positives — students need a provenance trail | E19: Education & Weird Gold | F19: Weird Gold / Education | G19: E1 | H19: 7.55 | I19: 8.5 | J19: 9.5 | K19: 8 | L19: 6.5 | M19: 6.5 | N19: 6.5 | O19: 8.5 | P19: 7.5 | Q19: 7 | R19: 4 | S19: PRO | T19: PRO | U19: 36 | V19: 30 | W19: N | Y19: r/Teachers: "False positives from AI detection in education destroyed my [relationship with students]... One of them cried in my office" (https://www.reddit.com/r/Teachers/comments/1oqozxw/); districts face lawsuits over false accusations (https://www.reddit.c
B20: 16 | C20: EC-C3 | D20: Shopify rejects CSVs for invisible format reasons: non-UTF-8 encoding, illegal characters, wrong quoting — ... | E20: E-commerce & SMB | F20: E-commerce & SMB Ops | G20: E1 | H20: 7.53 | I20: 7.5 | J20: 8 | K20: 9 | L20: 10 | M20: 6.5 | N20: 8 | O20: 5 | P20: 6 | Q20: 4.5 | R20: 4 | S20: PRO | T20: PRO | U20: 10 | V20: 10 | W20: N | Y20: Shopify rejects CSVs for invisible format reasons: non-UTF-8 encoding, illegal characters, wrong quoting — error messages are cryptic.
B21: 17 | C21: DV-B3 | D21: CORS errors remain a top chronic frustration — devs don't understand why requests fail and the error masks ... | E21: DevTools & Data | F21: Developer Tools | G21: E1 | H21: 7.53 | I21: 9 | J21: 8 | K21: 9 | L21: 8 | M21: 4.5 | N21: 9 | O21: 5 | P21: 6 | Q21: 8 | R21: 2.5 | S21: HOOK | T21: FREE | U21: 12 | V21: 10 | W21: N | X21: huge traffic pool; monetize via related dev-tool bundle rather than the checker itself. | Y21: CORS errors remain a top chronic frustration — devs don't understand why requests fail and the error masks the real problem.
B22: 18 | C22: DR-C4 | D22: Filled PDF form data disappears when printing/emailing/saving (form fields not flattened), and users don't ... | E22: Data & Repair | F22: Data & File Repair | G22: E1 | H22: 7.48 | I22: 7 | J22: 7.5 | K22: 7 | L22: 10 | M22: 6.5 | N22: 7 | O22: 5.5 | P22: 9.5 | Q22: 7 | R22: 6 | S22: PRO | T22: PRO | U22: 10 | V22: 10 | W22: N | Y22: Filled PDF form data disappears when printing/emailing/saving (form fields not flattened), and users don't know the term or the fix.
B23: 19 | C23: EC-C26 | D23: Bank-statement PDF→CSV: bookkeepers refuse "shady websites that claim to convert while also storing the dat... | E23: E-commerce & SMB | F23: E-commerce & SMB Ops | G23: E1 | H23: 7.42 | I23: 9.5 | J23: 8 | K23: 7 | L23: 8.5 | M23: 6 | N23: 5 | O23: 5 | P23: 9.5 | Q23: 4.5 | R23: 6 | S23: GLUE | T23: FREE | U23: 12 | V23: 10 | W23: N | Y23: Bank-statement PDF→CSV: bookkeepers refuse "shady websites that claim to convert while also storing the data" — trust/privacy is the wedge (complements task 2-a's price-umbrella finding: DocuClipper ~$49.95/mo, MoneyThumb ~$299.95).
B24: 20 | C24: DR-C2 | D24: Scanned PDFs have no text layer / OCR errors — users can't search, copy, or correct the text. | E24: Data & Repair | F24: Data & File Repair | G24: E1 | H24: 7.4 | I24: 8.5 | J24: 8 | K24: 9 | L24: 8.5 | M24: 6.5 | N24: 7 | O24: 6 | P24: 5 | Q24: 4.5 | R24: 4 | S24: PRO | T24: PRO | U24: 40 | V24: 45 | W24: Y | Y24: Scanned PDFs have no text layer / OCR errors — users can't search, copy, or correct the text.
B25: 21 | C25: DR-D1 | D25: Users are now *afraid* of free online converters — FBI + Malwarebytes confirm converter sites push malware/... | E25: Data & Repair | F25: Data & File Repair | G25: E1 | H25: 7.4 | I25: 8 | J25: 7 | K25: 5 | L25: 8.5 | M25: 6 | N25: 8 | O25: 5 | P25: 9.5 | Q25: 9 | R25: 8 | S25: HOOK | T25: FREE | U25: 12 | V25: 10 | W25: N | Y25: Users are now *afraid* of free online converters — FBI + Malwarebytes confirm converter sites push malware/ransomware; privacy of sensitive docs is the blocker.
B26: 22 | C26: DV-B10 | D26: MySQL→PostgreSQL (and reverse) migrations require manual SQL dialect rewrites — type mappings, quote styles... | E26: DevTools & Data | F26: Developer Tools | G26: E1 | H26: 7.4 | I26: 6.5 | J26: 8 | K26: 8 | L26: 8 | M26: 8 | N26: 8 | O26: 6.5 | P26: 9 | Q26: 4.5 | R26: 6 | S26: LTV | T26: PRO | U26: 12 | V26: 10 | W26: N | X26: paying audience + client-side feasible = strong rev-max candidate; correctness must be excellent. | Y26: MySQL→PostgreSQL (and reverse) migrations require manual SQL dialect rewrites — type mappings, quote styles, function differences — and simple converter tools are asked for repeatedly.
B27: 23 | C27: GT-JSON-json-DV-B2 | D27: JSON to CSV (flatten, arrays-safe) | E27: DevTools & Data | F27: Developer Tools | G27: E3 | H27: 7.4 | I27: 8 | J27: 6 | K27: 7 | L27: 10 | M27: 5 | N27: 9 | O27: 4 | P27: 10 | Q27: 8 | R27: 4 | S27: PRO | T27: PRO | U27: 12 | V27: 10 | W27: N | X27: json to csv converter | Y27: Long-tail tool instance: JSON to CSV (flatten, arrays-safe). Pattern-inherited pain evidence from DV-B2 cluster; ships as part of the mega-toolbox catalog (<=1 use/month tools included by directive).
B28: 24 | C28: GT-CSV-csv-DR-A1-2 | D28: Universal CSV Pre-flight Validator | E28: Data & Repair | F28: Data & File Repair | G28: E3 | H28: 7.4 | I28: 7 | J28: 6 | K28: 6 | L28: 10 | M28: 6 | N28: 9 | O28: 6 | P28: 10 | Q28: 9 | R28: 5 | S28: PRO | T28: PRO | U28: 18 | V28: 10 | W28: N | X28: csv validator online | Y28: Long-tail tool instance: Universal CSV Pre-flight Validator. Pattern-inherited pain evidence from DR-A1 cluster; ships as part of the mega-toolbox catalog (<=1 use/month tools included by directive).
B29: 25 | C29: GT-MKT-shopify-EC-C1 | D29: Shopify Product CSV Pre-flight Validator | E29: E-commerce & SMB | F29: E-commerce & SMB Ops | G29: E3 | H29: 7.4 | I29: 7 | J29: 8 | K29: 5 | L29: 9 | M29: 7 | N29: 9 | O29: 6 | P29: 8 | Q29: 8 | R29: 5 | S29: LTV | T29: PRO | U29: 30 | V29: 25 | W29: Y | X29: shopify csv import errors | Y29: Long-tail tool instance: Shopify Product CSV Pre-flight Validator. Pattern-inherited pain evidence from EC-C1 cluster; ships as part of the mega-toolbox catalog (<=1 use/month tools included by directive).
B30: 26 | C30: DR-F2 | D30: CSV→QBO/OFX conversions fail validator checks (bank IDs, dates, amounts) and accounting software silently r... | E30: Data & Repair | F30: Data & File Repair | G30: E1 | H30: 7.35 | I30: 7 | J30: 8.5 | K30: 7 | L30: 8.5 | M30: 8 | N30: 7.5 | O30: 3.5 | P30: 7.5 | Q30: 8 | R30: 4 | S30: PRO | T30: PRO | U30: 12 | V30: 10 | W30: N | Y30: CSV→QBO/OFX conversions fail validator checks (bank IDs, dates, amounts) and accounting software silently rejects or duplicates imports.
B31: 27 | C31: DR-F4 | D31: Banks simply don't offer CSV/data downloads for business accounts — statements are PDF-only — so conversion... | E31: Data & Repair | F31: Data & File Repair | G31: E1 | H31: 7.35 | I31: 8 | J31: 8.5 | K31: 4 | L31: 8.5 | M31: 8.5 | N31: 7 | O31: 7 | P31: 6 | Q31: 8 | R31: 4 | S31: LTV | T31: MAX | U31: 40 | V31: 45 | W31: Y | Y31: Banks simply don't offer CSV/data downloads for business accounts — statements are PDF-only — so conversion is forced on every bookkeeper.
B32: 28 | C32: DR-A1 | D32: Excel silently truncates/mangles big CSVs and strips leading zeros + rewrites dates, so re-imports into oth... | E32: Data & Repair | F32: Data & File Repair | G32: E1 | H32: 7.33 | I32: 9.5 | J32: 7 | K32: 9 | L32: 8.5 | M32: 6 | N32: 7 | O32: 3.5 | P32: 6 | Q32: 4.5 | R32: 4 | S32: GLUE | T32: FREE | U32: 12 | V32: 10 | W32: N | Y32: Excel silently truncates/mangles big CSVs and strips leading zeros + rewrites dates, so re-imports into other systems fail.
B33: 29 | C33: DV-B6 | D33: Postman gutted its free plan (Feb–Mar 2026: 1 user only, collaboration features removed, $14/mo/member) — a... | E33: DevTools & Data | F33: Developer Tools | G33: E1 | H33: 7.3 | I33: 8 | J33: 8 | K33: 4.5 | L33: 8.5 | M33: 6 | N33: 9 | O33: 6 | P33: 7.5 | Q33: 8 | R33: 4 | S33: HOOK | T33: FREE | U33: 12 | V33: 10 | W33: N | X33: build SMALL wedge not full client: "paste curl → get shareable request + response inspector, no install". Timeliness flagged. | Y33: Postman gutted its free plan (Feb–Mar 2026: 1 user only, collaboration features removed, $14/mo/member) — active anger window and migration search traffic.
B34: 30 | C34: GT-CSV-csv-DR-A1 | D34: CSV Delimiter Fixer | E34: Data & Repair | F34: Data & File Repair | G34: E3 | H34: 7.3 | I34: 7 | J34: 7 | K34: 6 | L34: 10 | M34: 5 | N34: 9 | O34: 5 | P34: 10 | Q34: 8 | R34: 4 | S34: PRO | T34: PRO | U34: 8 | V34: 10 | W34: N | X34: csv wrong delimiter fix | Y34: Long-tail tool instance: CSV Delimiter Fixer. Pattern-inherited pain evidence from DR-A1 cluster; ships as part of the mega-toolbox catalog (<=1 use/month tools included by directive).
B35: 31 | C35: DR-B1 | D35: LLM-generated and human-edited JSON breaks parsers on trailing commas, single quotes, comments, unquoted ke... | E35: Data & Repair | F35: Data & File Repair | G35: E1 | H35: 7.25 | I35: 8.5 | J35: 6 | K35: 9 | L35: 8.5 | M35: 5 | N35: 8 | O35: 3.5 | P35: 9.5 | Q35: 4.5 | R35: 6 | S35: HOOK | T35: FREE | U35: 12 | V35: 10 | W35: N | Y35: LLM-generated and human-edited JSON breaks parsers on trailing commas, single quotes, comments, unquoted keys — users hunt the offending char manually.
B36: 32 | C36: DR-C1 | D36: PDF→Excel conversion scrambles tables (merged cells, no grid lines, spanning headers) and users spend hours... | E36: Data & Repair | F36: Data & File Repair | G36: E1 | H36: 7.25 | I36: 9 | J36: 8.5 | K36: 9 | L36: 5.5 | M36: 7 | N36: 8.5 | O36: 3.5 | P36: 6 | Q36: 4.5 | R36: 4 | S36: PRO | T36: MAX | U36: 52 | V36: 45 | W36: Y | Y36: PDF→Excel conversion scrambles tables (merged cells, no grid lines, spanning headers) and users spend hours cleaning.
B37: 33 | C37: GT-CSV-find-DR-F1 | D37: Duplicate Row Finder (exact + fuzzy) | E37: Data & Repair | F37: Data & File Repair | G37: E3 | H37: 7.25 | I37: 7 | J37: 7 | K37: 5 | L37: 10 | M37: 6 | N37: 8 | O37: 6 | P37: 10 | Q37: 7 | R37: 5 | S37: PRO | T37: PRO | U37: 14 | V37: 10 | W37: N | X37: find duplicate rows csv | Y37: Long-tail tool instance: Duplicate Row Finder (exact + fuzzy). Pattern-inherited pain evidence from DR-F1 cluster; ships as part of the mega-toolbox catalog (<=1 use/month tools included by directive).
B38: 34 | C38: DR-A5 | D38: Marketplace/platform CSV imports (Shopify) fail on supplier CSVs because quoting, encoding, and column orde... | E38: Data & Repair | F38: Data & File Repair | G38: E1 | H38: 7.22 | I38: 7.5 | J38: 8 | K38: 7 | L38: 8.5 | M38: 8 | N38: 7 | O38: 5 | P38: 7.5 | Q38: 4.5 | R38: 4 | S38: PRO | T38: PRO | U38: 12 | V38: 10 | W38: N | Y38: Marketplace/platform CSV imports (Shopify) fail on supplier CSVs because quoting, encoding, and column order don't match Shopify's template.
B39: 35 | C39: EC-C1 | D39: "Supplier CSV import hell" — every supplier catalog update requires hours of manual fixing before Shopify a... | E39: E-commerce & SMB | F39: E-commerce & SMB Ops | G39: E1 | H39: 7.17 | I39: 7.5 | J39: 8.5 | K39: 7 | L39: 8 | M39: 7.5 | N39: 8.5 | O39: 3.5 | P39: 6 | Q39: 4.5 | R39: 4 | S39: PRO | T39: PRO | U39: 12 | V39: 10 | W39: N | Y39: "Supplier CSV import hell" — every supplier catalog update requires hours of manual fixing before Shopify accepts it: merged columns, wrong headers, images not importing, variants scrambled, "illegal quoting" errors.
B40: 36 | C40: DR-A6 | D40: Files >1M rows can't be opened in Excel — users need to split huge CSVs and don't know how. | E40: Data & Repair | F40: Data & File Repair | G40: E1 | H40: 7.15 | I40: 7.5 | J40: 7 | K40: 7 | L40: 10 | M40: 6 | N40: 7 | O40: 3.5 | P40: 7.5 | Q40: 7 | R40: 4 | S40: GLUE | T40: FREE | U40: 10 | V40: 10 | W40: N | Y40: Files >1M rows can't be opened in Excel — users need to split huge CSVs and don't know how.
B41: 37 | C41: EC-C7 | D41: Multichannel inventory sync (Shopify+Etsy+eBay+Amazon+POS) for tiny sellers = overselling risk; enterprise ... | E41: E-commerce & SMB | F41: E-commerce & SMB Ops | G41: E1 | H41: 7.15 | I41: 6.5 | J41: 8 | K41: 9 | L41: 8.5 | M41: 7 | N41: 7 | O41: 5.5 | P41: 7.5 | Q41: 4.5 | R41: 4 | S41: PRO | T41: PRO | U41: 12 | V41: 10 | W41: N | Y41: Multichannel inventory sync (Shopify+Etsy+eBay+Amazon+POS) for tiny sellers = overselling risk; enterprise sync tools are overkill/too pricey, so sellers juggle spreadsheets.
B42: 38 | C42: GT-JSON-fix-DV-B20 | D42: JSON Repair / Error Fixer | E42: DevTools & Data | F42: Developer Tools | G42: E3 | H42: 7.15 | I42: 7 | J42: 7 | K42: 6 | L42: 10 | M42: 5 | N42: 8 | O42: 5 | P42: 10 | Q42: 7 | R42: 4 | S42: PRO | T42: PRO | U42: 10 | V42: 25 | W42: Y | X42: fix invalid json online | Y42: Long-tail tool instance: JSON Repair / Error Fixer. Pattern-inherited pain evidence from DV-B20 cluster; ships as part of the mega-toolbox catalog (<=1 use/month tools included by directive).
B43: 39 | C43: GT-CSV-convert-DR-A2 | D43: CSV Encoding Converter (UTF-8/GBK/1252) | E43: Data & Repair | F43: Data & File Repair | G43: E3 | H43: 7.15 | I43: 7 | J43: 7 | K43: 5 | L43: 10 | M43: 5 | N43: 9 | O43: 5 | P43: 10 | Q43: 7 | R43: 4 | S43: PRO | T43: PRO | U43: 10 | V43: 10 | W43: N | X43: convert csv encoding utf-8 | Y43: Long-tail tool instance: CSV Encoding Converter (UTF-8/GBK/1252). Pattern-inherited pain evidence from DR-A2 cluster; ships as part of the mega-toolbox catalog (<=1 use/month tools included by directive).
B44: 40 | C44: DR-G3 | D44: PDF-pasted or exported text arrives with broken line breaks/mid-word wraps, and cleaning it into one-row-pe... | E44: Data & Repair | F44: Data & File Repair | G44: E3 | H44: 7.12 | I44: 8 | J44: 6.5 | K44: 8 | L44: 10 | M44: 5 | N44: 7 | O44: 5 | P44: 7.5 | Q44: 4.5 | R44: 4 | S44: GLUE | T44: FREE | U44: 10 | V44: 10 | W44: N | Y44: PDF-pasted or exported text arrives with broken line breaks/mid-word wraps, and cleaning it into one-row-per-record is manual.
B45: 41 | C45: WG-G17 | D45: BCS & competitive-exam prep: question banks exist, access costs | E45: Education & Weird Gold | F45: Weird Gold / Education | G45: E2 | H45: 7.12 | I45: 8.5 | J45: 6 | K45: 8 | L45: 6.5 | M45: 6 | N45: 8 | O45: 6 | P45: 7.5 | Q45: 8 | R45: 5.5 | S45: HOOK | T45: FREE | U45: 36 | V45: 30 | W45: N | Y45: scale of demand: Ogroshor claims "1,600,847+ questions" practice bank (https://ogroshor.com); Studypress markets "All BCS 10th–45th questions and solutions" (https://studypress.org); Android apps with 100k+ MCQs (https://play.google.com/store/apps/details?id=c
B46: 42 | C46: DR-G2 | D46: Merged cells destroy sort/filter/pivot operations; analysts inherit "pretty" reports and must un-merge + ba... | E46: Data & Repair | F46: Data & File Repair | G46: E1 | H46: 7.1 | I46: 8 | J46: 7.5 | K46: 7 | L46: 10 | M46: 5 | N46: 7 | O46: 3.5 | P46: 7.5 | Q46: 4.5 | R46: 4 | S46: GLUE | T46: FREE | U46: 10 | V46: 10 | W46: N | Y46: Merged cells destroy sort/filter/pivot operations; analysts inherit "pretty" reports and must un-merge + backfill.
B47: 43 | C47: WG-G1 | D47: Quizlet paywall betrayal — teachers can't assign study modes anymore | E47: Education & Weird Gold | F47: Weird Gold / Education | G47: E1 | H47: 7.1 | I47: 8.5 | J47: 7 | K47: 7.5 | L47: 6.5 | M47: 6 | N47: 8 | O47: 6 | P47: 7.5 | Q47: 7 | R47: 4 | S47: HOOK | T47: FREE | U47: 36 | V47: 30 | W47: N | Y47: r/Teachers: "I rely heavily on Quizlet but now its main mode is no longer free so I can't expect students to use it" (https://www.reddit.com/r/Teachers/comments/x3a1lg/); r/quizlet: "extremely disappointed and saddened... two of their most essential learning t
B48: 44 | C48: GT-JSON-csv-DV-B2 | D48: CSV to JSON | E48: DevTools & Data | F48: Developer Tools | G48: E3 | H48: 7.1 | I48: 8 | J48: 5 | K48: 7 | L48: 10 | M48: 4 | N48: 9 | O48: 4 | P48: 10 | Q48: 7 | R48: 4 | S48: HOOK | T48: FREE | U48: 8 | V48: 10 | W48: N | X48: csv to json converter | Y48: Long-tail tool instance: CSV to JSON. Pattern-inherited pain evidence from DV-B2 cluster; ships as part of the mega-toolbox catalog (<=1 use/month tools included by directive).
B49: 45 | C49: EC-C6 | D49: Supplier price/stock scheduled sync: tiny dropshippers must periodically re-pull supplier CSV/FTP feeds and... | E49: E-commerce & SMB | F49: E-commerce & SMB Ops | G49: E1 | H49: 7.05 | I49: 6 | J49: 7.5 | K49: 9 | L49: 8.5 | M49: 6.5 | N49: 7 | O49: 7 | P49: 6 | Q49: 7 | R49: 4 | S49: PRO | T49: PRO | U49: 12 | V49: 10 | W49: N | Y49: Supplier price/stock scheduled sync: tiny dropshippers must periodically re-pull supplier CSV/FTP feeds and update Shopify price+inventory; manual process causes stale stock and overselling.
B50: 46 | C50: WG-G6 | D50: De-slopping AI text (writers/marketers) | E50: Education & Weird Gold | F50: Weird Gold / Education | G50: E1 | H50: 7.05 | I50: 8.5 | J50: 6 | K50: 9 | L50: 6.5 | M50: 7 | N50: 9 | O50: 3.5 | P50: 7.5 | Q50: 4.5 | R50: 4 | S50: PRO | T50: PRO | U50: 36 | V50: 30 | W50: N | Y50: "the actual job became editing AI drafts and nobody warned me the editing is harder than the writing" (https://www.reddit.com/r/content_marketing/comments/1v39e5a/); "HOW TO REMOVE AI SLOP FROM YOUR WRITING" guides (https://www.reddit.com/r/WritingWithAI/comme
B51: 47 | C51: DR-B3 | D51: JSON↔CSV conversion of nested data is "almost impossible" for practitioners — array-of-struct nesting flatt... | E51: Data & Repair | F51: Data & File Repair | G51: E1 | H51: 7.03 | I51: 8 | J51: 8 | K51: 7 | L51: 8 | M51: 6 | N51: 7 | O51: 3.5 | P51: 6 | Q51: 7 | R51: 4 | S51: GLUE | T51: FREE | U51: 12 | V51: 10 | W51: N | Y51: JSON↔CSV conversion of nested data is "almost impossible" for practitioners — array-of-struct nesting flattens wrong, columns explode.
B52: 48 | C52: DR-G1 | D52: Fuzzy duplicate removal (same company with typos/abbreviations) is beyond Excel's exact-match Remove Duplic... | E52: Data & Repair | F52: Data & File Repair | G52: E1 | H52: 7.03 | I52: 7 | J52: 7.5 | K52: 7 | L52: 8.5 | M52: 6.5 | N52: 7 | O52: 3.5 | P52: 9.5 | Q52: 4.5 | R52: 6 | S52: PRO | T52: PRO | U52: 12 | V52: 10 | W52: N | Y52: Fuzzy duplicate removal (same company with typos/abbreviations) is beyond Excel's exact-match Remove Duplicates.
B53: 49 | C53: EC-C9 | D53: "Amazon flat file formatting is hell": category templates keep changing, one blank required field fails the... | E53: E-commerce & SMB | F53: E-commerce & SMB Ops | G53: E1 | H53: 7.03 | I53: 7 | J53: 8.5 | K53: 5 | L53: 8.5 | M53: 7.5 | N53: 7 | O53: 6.5 | P53: 7.5 | Q53: 4.5 | R53: 4 | S53: LTV | T53: PRO | U53: 12 | V53: 10 | W53: N | Y53: "Amazon flat file formatting is hell": category templates keep changing, one blank required field fails the whole row, Data Definitions tab archaeology, character limits per field.
B54: 50 | C54: EC-C15 | D54: Google Merchant Center disapprovals spike suddenly and in bulk: price-mismatch, missing GTIN, misclassified... | E54: E-commerce & SMB | F54: E-commerce & SMB Ops | G54: E1 | H54: 7.03 | I54: 6.5 | J54: 8 | K54: 8 | L54: 8.5 | M54: 7 | N54: 7 | O54: 6.5 | P54: 6 | Q54: 4.5 | R54: 4 | S54: LTV | T54: PRO | U54: 12 | V54: 10 | W54: N | Y54: Google Merchant Center disapprovals spike suddenly and in bulk: price-mismatch, missing GTIN, misclassified policy flags (e.g., 530 products flagged "Alcoholic drinks" wrongly); fixes require per-attribute edits across the feed.
B55: 51 | C55: GT-CSV-xlsx-DR-A1 | D55: XLSX to CSV / CSV to XLSX | E55: Data & Repair | F55: Data & File Repair | G55: E3 | H55: 7 | I55: 8 | J55: 5 | K55: 7 | L55: 10 | M55: 4 | N55: 9 | O55: 4 | P55: 10 | Q55: 6 | R55: 3 | S55: HOOK | T55: FREE | U55: 10 | V55: 10 | W55: N | X55: xlsx to csv converter | Y55: Long-tail tool instance: XLSX to CSV / CSV to XLSX. Pattern-inherited pain evidence from DR-A1 cluster; ships as part of the mega-toolbox catalog (<=1 use/month tools included by directive).
B56: 52 | C56: GT-MKT-amazon-EC-C9 | D56: Amazon Flat File Pre-flight (8541 etc.) | E56: E-commerce & SMB | F56: E-commerce & SMB Ops | G56: E3 | H56: 7 | I56: 6 | J56: 8 | K56: 4 | L56: 9 | M56: 7 | N56: 8 | O56: 6 | P56: 8 | Q56: 8 | R56: 5 | S56: LTV | T56: PRO | U56: 35 | V56: 25 | W56: Y | X56: amazon flat file errors | Y56: Long-tail tool instance: Amazon Flat File Pre-flight (8541 etc.). Pattern-inherited pain evidence from EC-C9 cluster; ships as part of the mega-toolbox catalog (<=1 use/month tools included by directive).
B57: 53 | C57: EC-C8 | D57: Amazon error 8541 ("single matching error") blocks listing/edits when product ID matches an existing ASIN w... | E57: E-commerce & SMB | F57: E-commerce & SMB Ops | G57: E1 | H57: 6.98 | I57: 6.5 | J57: 8 | K57: 8 | L57: 8.5 | M57: 6 | N57: 7 | O57: 6 | P57: 7.5 | Q57: 4.5 | R57: 4 | S57: GLUE | T57: FREE | U57: 12 | V57: 10 | W57: N | Y57: Amazon error 8541 ("single matching error") blocks listing/edits when product ID matches an existing ASIN with conflicting attributes; fix workflow is arcane (flat file partial update, product ID toggling).
B58: 54 | C58: DV-B2 | D58: JSON ↔ JSONL (JSON Lines) conversion confusion — devs routinely ask how to convert arrays to JSONL and back... | E58: DevTools & Data | F58: Developer Tools | G58: E1 | H58: 6.98 | I58: 7.5 | J58: 6 | K58: 7 | L58: 10 | M58: 5 | N58: 7 | O58: 3.5 | P58: 9.5 | Q58: 4.5 | R58: 6 | S58: GLUE | T58: FREE | U58: 10 | V58: 10 | W58: N | X58: validated demand + fragmented low-trust supply = classic micro-tool opening. | Y58: JSON ↔ JSONL (JSON Lines) conversion confusion — devs routinely ask how to convert arrays to JSONL and back for ML training data, logs, and APIs.
B59: 55 | C59: GT-JSON-json-DV-B1 | D59: JSON Formatter & Validator | E59: DevTools & Data | F59: Developer Tools | G59: E3 | H59: 6.95 | I59: 8 | J59: 4 | K59: 9 | L59: 10 | M59: 4 | N59: 8 | O59: 3 | P59: 10 | Q59: 7 | R59: 3 | S59: HOOK | T59: FREE | U59: 6 | V59: 10 | W59: N | X59: json formatter online | Y59: Long-tail tool instance: JSON Formatter & Validator. Pattern-inherited pain evidence from DV-B1 cluster; ships as part of the mega-toolbox catalog (<=1 use/month tools included by directive).
B60: 56 | C60: DV-B7 | D60: Webhook testing requires a public URL + request inspection — existing free tools have limits and the workfl... | E60: DevTools & Data | F60: Developer Tools | G60: E1 | H60: 6.92 | I60: 6.5 | J60: 6 | K60: 7 | L60: 10 | M60: 6.5 | N60: 7 | O60: 5.5 | P60: 6 | Q60: 8 | R60: 4 | S60: PRO | T60: PRO | U60: 10 | V60: 10 | W60: N | X60: pairs with B8 (tunnels) into one "webhook workspace" micro-product. | Y60: Webhook testing requires a public URL + request inspection — existing free tools have limits and the workflow spans 3+ tools (tunnel + bin + replayer).
B61: 57 | C61: WG-G20 | D61: Spreadsheets-as-products: people repeatedly ask "how do I build X in Excel/Sheets" — and PAY for templates | E61: Education & Weird Gold | F61: Weird Gold / Education | G61: E1 | H61: 6.9 | I61: 8 | J61: 5 | K61: 8 | L61: 6.5 | M61: 6.5 | N61: 8 | O61: 6 | P61: 7.5 | Q61: 9 | R61: 4 | S61: PRO | T61: PRO | U61: 36 | V61: 30 | W61: N | Y61: tenant-ledger spreadsheets are SOLD on Etsy (https://www.etsy.com/market/tenant_ledger_spreadsheet); gig drivers maintain community spreadsheets (https://www.reddit.com/r/DoorDashDrivers/comments/199idff/; https://www.facebook.com/groups/1457430271994284/posts
B62: 58 | C62: GT-PDF-compress-DR-C1 | D62: PDF Compressor | E62: Data & Repair | F62: Data & File Repair | G62: E3 | H62: 6.9 | I62: 9 | J62: 5 | K62: 6 | L62: 10 | M62: 5 | N62: 9 | O62: 2 | P62: 8 | Q62: 5 | R62: 2 | S62: HOOK | T62: FREE | U62: 12 | V62: 10 | W62: N | X62: compress pdf online free | Y62: Long-tail tool instance: PDF Compressor. Pattern-inherited pain evidence from DR-C1 cluster; ships as part of the mega-toolbox catalog (<=1 use/month tools included by directive).
B63: 59 | C63: GT-TG-telegram-platform | D63: Telegram Mini App Shell (Stars-native checkout) | E63: BD & Telegram | F63: Telegram / BD | G63: E3 | H63: 6.9 | I63: 8 | J63: 5 | K63: 7 | L63: 7 | M63: 7 | N63: 8 | O63: 5 | P63: 6 | Q63: 9 | R63: 6 | S63: LTV | T63: MAX | U63: 60 | V63: 30 | W63: N | X63: telegram mini app tools | Y63: Long-tail tool instance: Telegram Mini App Shell (Stars-native checkout). Pattern-inherited pain evidence from platform cluster; ships as part of the mega-toolbox catalog (<=1 use/month tools included by directive).
B64: 60 | C64: EC-C5 | D64: Shopify still has NO native way to import/edit metafields via product CSV — users resort to third-party app... | E64: E-commerce & SMB | F64: E-commerce & SMB Ops | G64: E1 | H64: 6.88 | I64: 6.5 | J64: 7.5 | K64: 8 | L64: 8.5 | M64: 6.5 | N64: 7 | O64: 6 | P64: 6 | Q64: 4.5 | R64: 4 | S64: PRO | T64: PRO | U64: 12 | V64: 10 | W64: N | Y64: Shopify still has NO native way to import/edit metafields via product CSV — users resort to third-party apps and call it crazy.
B65: 61 | C65: EC-C18 | D65: Bulk product-photo background removal & processing costs anger small catalogs: outsourcing $2–7/image, per-... | E65: E-commerce & SMB | F65: E-commerce & SMB Ops | G65: E1 | H65: 6.88 | I65: 7.5 | J65: 7 | K65: 5 | L65: 8.5 | M65: 6 | N65: 7 | O65: 5 | P65: 9.5 | Q65: 4.5 | R65: 6 | S65: GLUE | T65: FREE | U65: 12 | V65: 10 | W65: N | Y65: Bulk product-photo background removal & processing costs anger small catalogs: outsourcing $2–7/image, per-image SaaS fees ($0.20–$1.50) "add up extremely fast"; sellers want bulk/one-time/local processing.
B66: 62 | C66: WG-G10 | D66: Gig-driver income/expense/mileage tracking | E66: Education & Weird Gold | F66: Weird Gold / Education | G66: E1 | H66: 6.85 | I66: 8.5 | J66: 6 | K66: 9 | L66: 6.5 | M66: 6 | N66: 6 | O66: 3.5 | P66: 7.5 | Q66: 7 | R66: 5.5 | S66: GLUE | T66: FREE | U66: 36 | V66: 30 | W66: N | Y66: r/GigWork: "how do you keep track of how much you're making vs. what you're spending?" (https://www.reddit.com/r/GigWork/comments/1id6uyo/); a dev built MileLog "after getting tired of messy spreadsheets" and launched free on r/uberdrivers (https://www.reddit.
B67: 63 | C67: GT-JSON-json-DV-B1-2 | D67: JSON Diff Checker | E67: DevTools & Data | F67: Developer Tools | G67: E3 | H67: 6.85 | I67: 7 | J67: 5 | K67: 7 | L67: 10 | M67: 5 | N67: 8 | O67: 4 | P67: 10 | Q67: 6 | R67: 4 | S67: HOOK | T67: FREE | U67: 10 | V67: 10 | W67: N | X67: json diff online | Y67: Long-tail tool instance: JSON Diff Checker. Pattern-inherited pain evidence from DV-B1 cluster; ships as part of the mega-toolbox catalog (<=1 use/month tools included by directive).
B68: 64 | C68: GT-JSON-json-DV-B14 | D68: JSON to TypeScript / Go / Java Types | E68: DevTools & Data | F68: Developer Tools | G68: E3 | H68: 6.85 | I68: 7 | J68: 5 | K68: 6 | L68: 10 | M68: 5 | N68: 8 | O68: 6 | P68: 10 | Q68: 7 | R68: 3 | S68: HOOK | T68: FREE | U68: 16 | V68: 10 | W68: N | X68: json to typescript | Y68: Long-tail tool instance: JSON to TypeScript / Go / Java Types. Pattern-inherited pain evidence from DV-B14 cluster; ships as part of the mega-toolbox catalog (<=1 use/month tools included by directive).
B69: 65 | C69: WG-G16 | D69: Podcast show notes — "one of the most hated steps of podcasting" | E69: Education & Weird Gold | F69: Weird Gold / Education | G69: E1 | H69: 6.83 | I69: 8.5 | J69: 6 | K69: 7 | L69: 6.5 | M69: 6 | N69: 7 | O69: 5 | P69: 7.5 | Q69: 7 | R69: 5.5 | S69: GLUE | T69: FREE | U69: 36 | V69: 30 | W69: N | Y69: School of Podcasting: "One of the most hated steps of podcasting is writing show notes" (https://www.schoolofpodcasting.com/tackling-show-notes-how-long-should-my-notes-be); r/podcasting thread on show-notes time sinks (https://www.reddit.com/r/podcasting/comm
B70: 66 | C70: DR-S3 | D70: YouTube auto-generated VTT subs convert to SRT with the same line repeated 2-4x and inline timestamps — con... | E70: Data & Repair | F70: Data & File Repair | G70: E1 | H70: 6.8 | I70: 6 | J70: 7.5 | K70: 7 | L70: 10 | M70: 5 | N70: 8 | O70: 3.5 | P70: 7.5 | Q70: 4.5 | R70: 4 | S70: GLUE | T70: FREE | U70: 10 | V70: 10 | W70: N | Y70: YouTube auto-generated VTT subs convert to SRT with the same line repeated 2-4x and inline timestamps — converters break.
B71: 67 | C71: GT-CSV-merge-DR-B2 | D71: CSV Merger / Concatenator | E71: Data & Repair | F71: Data & File Repair | G71: E3 | H71: 6.8 | I71: 7 | J71: 5 | K71: 5 | L71: 10 | M71: 4 | N71: 9 | O71: 5 | P71: 10 | Q71: 8 | R71: 4 | S71: HOOK | T71: FREE | U71: 8 | V71: 10 | W71: N | X71: merge csv files online | Y71: Long-tail tool instance: CSV Merger / Concatenator. Pattern-inherited pain evidence from DR-B2 cluster; ships as part of the mega-toolbox catalog (<=1 use/month tools included by directive).
B72: 68 | C72: DR-S1 | D72: Downloaded subtitles are out of sync by a fixed offset (or drift due to FPS mismatch) and casual users can'... | E72: Data & Repair | F72: Data & File Repair | G72: E1 | H72: 6.78 | I72: 6.5 | J72: 6 | K72: 9 | L72: 10 | M72: 5 | N72: 7 | O72: 3.5 | P72: 7.5 | Q72: 4.5 | R72: 4 | S72: GLUE | T72: FREE | U72: 10 | V72: 10 | W72: N | Y72: Downloaded subtitles are out of sync by a fixed offset (or drift due to FPS mismatch) and casual users can't fix them.
B73: 69 | C73: EC-C22 | D73: Reconciling Stripe/PayPal/processor CSVs against bank settlements: fees, refunds, and payout netting make r... | E73: E-commerce & SMB | F73: E-commerce & SMB Ops | G73: E1 | H73: 6.78 | I73: 6.5 | J73: 8 | K73: 4 | L73: 8.5 | M73: 7.5 | N73: 7 | O73: 7 | P73: 7.5 | Q73: 4.5 | R73: 4 | S73: LTV | T73: PRO | U73: 12 | V73: 10 | W73: N | Y73: Reconciling Stripe/PayPal/processor CSVs against bank settlements: fees, refunds, and payout netting make rows not line up; month-end becomes a "nightmare".
B74: 70 | C74: GT-PDF-merge-DR-C1 | D74: PDF Merge | E74: Data & Repair | F74: Data & File Repair | G74: E3 | H74: 6.75 | I74: 9 | J74: 4 | K74: 7 | L74: 10 | M74: 4 | N74: 9 | O74: 2 | P74: 8 | Q74: 5 | R74: 2 | S74: HOOK | T74: FREE | U74: 8 | V74: 10 | W74: N | X74: merge pdf online free | Y74: Long-tail tool instance: PDF Merge. Pattern-inherited pain evidence from DR-C1 cluster; ships as part of the mega-toolbox catalog (<=1 use/month tools included by directive).
B75: 71 | C75: GT-PDF-flatten-DR-C4 | D75: PDF Form Flattener | E75: Data & Repair | F75: Data & File Repair | G75: E3 | H75: 6.75 | I75: 6 | J75: 7 | K75: 4 | L75: 10 | M75: 6 | N75: 8 | O75: 5 | P75: 8 | Q75: 7 | R75: 4 | S75: PRO | T75: PRO | U75: 10 | V75: 10 | W75: N | X75: flatten pdf form online | Y75: Long-tail tool instance: PDF Form Flattener. Pattern-inherited pain evidence from DR-C4 cluster; ships as part of the mega-toolbox catalog (<=1 use/month tools included by directive).
B76: 72 | C76: GT-IMG-compress-EC-C10 | D76: Image Compressor (WASM mozjpeg/avif) | E76: Media & Image | F76: Media & Image | G76: E3 | H76: 6.75 | I76: 9 | J76: 4 | K76: 6 | L76: 10 | M76: 5 | N76: 9 | O76: 2 | P76: 8 | Q76: 5 | R76: 2 | S76: HOOK | T76: FREE | U76: 25 | V76: 10 | W76: N | X76: compress jpeg online | Y76: Long-tail tool instance: Image Compressor (WASM mozjpeg/avif). Pattern-inherited pain evidence from EC-C10 cluster; ships as part of the mega-toolbox catalog (<=1 use/month tools included by directive).
B77: 73 | C77: GT-EDU-bcs-WG-G17 | D77: MCQ Practice Web App + Telegram Bot | E77: Education & Weird Gold | F77: Weird Gold / Education | G77: E3 | H77: 6.75 | I77: 7 | J77: 6 | K77: 7 | L77: 7 | M77: 6 | N77: 8 | O77: 6 | P77: 6 | Q77: 8 | R77: 6 | S77: LTV | T77: PRO | U77: 60 | V77: 30 | W77: N | X77: bcs question bank online | Y77: Long-tail tool instance: MCQ Practice Web App + Telegram Bot. Pattern-inherited pain evidence from WG-G17 cluster; ships as part of the mega-toolbox catalog (<=1 use/month tools included by directive).
B78: 74 | C78: DR-A3 | D78: CSV files with wrong/legacy encoding (Windows-1252, Latin-1, MacRoman) show mojibake ("Ã©", "â€™") downstre... | E78: Data & Repair | F78: Data & File Repair | G78: E1 | H78: 6.73 | I78: 8 | J78: 7.5 | K78: 7 | L78: 8.5 | M78: 2.5 | N78: 9 | O78: 4.5 | P78: 6 | Q78: 4.5 | R78: 2.5 | S78: HOOK | T78: FREE | U78: 12 | V78: 10 | W78: N | Y78: CSV files with wrong/legacy encoding (Windows-1252, Latin-1, MacRoman) show mojibake ("Ã©", "â€™") downstream and break imports.
B79: 75 | C79: WG-G9 | D79: Landlord rent ledgers — especially IRREGULAR payments | E79: Education & Weird Gold | F79: Weird Gold / Education | G79: E1 | H79: 6.73 | I79: 7 | J79: 8.5 | K79: 4 | L79: 6.5 | M79: 7.5 | N79: 7 | O79: 8.5 | P79: 6 | Q79: 6 | R79: 4 | S79: LTV | T79: MAX | U79: 40 | V79: 45 | W79: N | Y79: r/Landlord: "Can anyone suggest a basic and FREE software" (https://www.reddit.com/r/Landlord/comments/13rft38/); r/Landlord: income/expense tracking "starting to get overwhelming" (https://www.reddit.com/r/Landlord/comments/1hwh9u1/); r/AusPropertyChat: "trac
B80: 76 | C80: GT-CSV-clean-DR-A1 | D80: CSV Cleaner (trim/quotes/blank rows) | E80: Data & Repair | F80: Data & File Repair | G80: E3 | H80: 6.7 | I80: 6 | J80: 6 | K80: 5 | L80: 10 | M80: 5 | N80: 8 | O80: 6 | P80: 10 | Q80: 7 | R80: 3 | S80: PRO | T80: PRO | U80: 12 | V80: 10 | W80: N | X80: clean csv data online | Y80: Long-tail tool instance: CSV Cleaner (trim/quotes/blank rows). Pattern-inherited pain evidence from DR-A1 cluster; ships as part of the mega-toolbox catalog (<=1 use/month tools included by directive).
B81: 77 | C81: GT-SUB-shift-DR-S2 | D81: SRT Offset / Timeshift Tool | E81: Data & Repair | F81: Data & File Repair | G81: E3 | H81: 6.7 | I81: 6 | J81: 7 | K81: 4 | L81: 10 | M81: 4 | N81: 9 | O81: 4 | P81: 10 | Q81: 7 | R81: 4 | S81: GLUE | T81: FREE | U81: 6 | V81: 10 | W81: N | X81: shift srt subtitles | Y81: Long-tail tool instance: SRT Offset / Timeshift Tool. Pattern-inherited pain evidence from DR-S2 cluster; ships as part of the mega-toolbox catalog (<=1 use/month tools included by directive).
B82: 78 | C82: EC-C20 | D82: WooCommerce import monopoly pricing: WP All Import is "massive price tag" ($99–229/yr, reported) and users ... | E82: E-commerce & SMB | F82: E-commerce & SMB Ops | G82: E1 | H82: 6.65 | I82: 6 | J82: 7 | K82: 8 | L82: 8.5 | M82: 6.5 | N82: 5 | O82: 6.5 | P82: 6 | Q82: 7 | R82: 4 | S82: PRO | T82: PRO | U82: 12 | V82: 10 | W82: N | Y82: WooCommerce import monopoly pricing: WP All Import is "massive price tag" ($99–229/yr, reported) and users can't find decent alternatives; built-in Woo importer lacks scheduling/field-mapping power.
B83: 79 | C83: GT-PDF-split-DR-C1 | D83: PDF Split / Extract Range | E83: Data & Repair | F83: Data & File Repair | G83: E3 | H83: 6.65 | I83: 9 | J83: 4 | K83: 6 | L83: 10 | M83: 4 | N83: 9 | O83: 2 | P83: 8 | Q83: 5 | R83: 2 | S83: HOOK | T83: FREE | U83: 8 | V83: 10 | W83: N | X83: split pdf online free | Y83: Long-tail tool instance: PDF Split / Extract Range. Pattern-inherited pain evidence from DR-C1 cluster; ships as part of the mega-toolbox catalog (<=1 use/month tools included by directive).
B84: 80 | C84: DR-F5 | D84: WooCommerce product CSV imports fail on image URLs ("unable to use image"), server limits, and Excel-mangle... | E84: Data & Repair | F84: Data & File Repair | G84: E1 | H84: 6.62 | I84: 6 | J84: 7.5 | K84: 7 | L84: 8.5 | M84: 6.5 | N84: 7 | O84: 3.5 | P84: 7.5 | Q84: 4.5 | R84: 4 | S84: PRO | T84: PRO | U84: 12 | V84: 10 | W84: N | Y84: WooCommerce product CSV imports fail on image URLs ("unable to use image"), server limits, and Excel-mangled files.
B85: 81 | C85: EC-C17 | D85: Product-feed management tools price out tiny sellers: feed optimization starts ~$59–64/mo while small selle... | E85: E-commerce & SMB | F85: E-commerce & SMB Ops | G85: E1 | H85: 6.62 | I85: 6.5 | J85: 7 | K85: 5 | L85: 8.5 | M85: 7 | N85: 7 | O85: 6 | P85: 7.5 | Q85: 4.5 | R85: 4 | S85: LTV | T85: PRO | U85: 12 | V85: 10 | W85: N | Y85: Product-feed management tools price out tiny sellers: feed optimization starts ~$59–64/mo while small sellers just need error fixes + a few field rules.
B86: 82 | C86: WG-G15 | D86: Wedding planning spreadsheets (guest list hell) | E86: Education & Weird Gold | F86: Weird Gold / Education | G86: E1 | H86: 6.62 | I86: 8.5 | J86: 5 | K86: 8 | L86: 6.5 | M86: 5 | N86: 8 | O86: 5 | P86: 6 | Q86: 7 | R86: 4 | S86: HOOK | T86: FREE | U86: 40 | V86: 45 | W86: N | Y86: r/weddingplanning constantly exchanges/begs for spreadsheets: template thread (https://www.reddit.com/r/weddingplanning/comments/1bz4g8n/), "Struggling with how to even start making a guest list" using Excel columns (https://www.reddit.com/r/weddingplanning/co
B87: 83 | C87: DR-F3 | D87: Invoice/receipt data extraction tools are priced for enterprises ($500-$1,500/mo floors), locking out small... | E87: Data & Repair | F87: Data & File Repair | G87: E2 | H87: 6.6 | I87: 6.5 | J87: 8 | K87: 7 | L87: 5.5 | M87: 8 | N87: 7 | O87: 7.5 | P87: 5.5 | Q87: 4.5 | R87: 4 | S87: LTV | T87: MAX | U87: 52 | V87: 45 | W87: Y | Y87: Invoice/receipt data extraction tools are priced for enterprises ($500-$1,500/mo floors), locking out small businesses who just have a folder of PDFs.
B88: 84 | C88: EC-C4 | D88: Shopify CSV variant semantics are unforgiving: sorting rows breaks variant↔image links, duplicate option va... | E88: E-commerce & SMB | F88: E-commerce & SMB Ops | G88: E1 | H88: 6.6 | I88: 6.5 | J88: 7.5 | K88: 5 | L88: 8.5 | M88: 6.5 | N88: 7 | O88: 5 | P88: 7.5 | Q88: 4.5 | R88: 4 | S88: PRO | T88: PRO | U88: 12 | V88: 10 | W88: N | Y88: Shopify CSV variant semantics are unforgiving: sorting rows breaks variant↔image links, duplicate option values error out, one image per variant limit, Handle/Variant-ID bookkeeping overwrites or duplicates products.
B89: 85 | C89: GT-SEC-qr-DV-B20 | D89: QR Code Generator (logo + batch) | E89: Web & Text Utilities | F89: Web & Text Utilities | G89: E3 | H89: 6.6 | I89: 9 | J89: 3 | K89: 5 | L89: 10 | M89: 5 | N89: 9 | O89: 2 | P89: 9 | Q89: 6 | R89: 2 | S89: HOOK | T89: FREE | U89: 16 | V89: 10 | W89: N | X89: qr code generator free | Y89: Long-tail tool instance: QR Code Generator (logo + batch). Pattern-inherited pain evidence from DV-B20 cluster; ships as part of the mega-toolbox catalog (<=1 use/month tools included by directive).
B90: 86 | C90: EC-C10 | D90: Etsy has no real CSV import for listing edits; sellers enter variants by hand or pay for limited uploaders;... | E90: E-commerce & SMB | F90: E-commerce & SMB Ops | G90: E1 | H90: 6.58 | I90: 6 | J90: 7.5 | K90: 5 | L90: 8.5 | M90: 6.5 | N90: 7 | O90: 6.5 | P90: 7.5 | Q90: 4.5 | R90: 4 | S90: PRO | T90: PRO | U90: 12 | V90: 10 | W90: N | Y90: Etsy has no real CSV import for listing edits; sellers enter variants by hand or pay for limited uploaders; Etsy's native CSV upload is new-listing-only and variant-awkward.
B91: 87 | C91: DV-B5 | D91: Converting curl commands (copied from docs/DevTools) into Python/JS/PHP code is a standing need — proven by... | E91: DevTools & Data | F91: Developer Tools | G91: E2 | H91: 6.58 | I91: 6.5 | J91: 5 | K91: 9 | L91: 8.5 | M91: 5 | N91: 7 | O91: 3.5 | P91: 7.5 | Q91: 8 | R91: 4 | S91: GLUE | T91: FREE | U91: 12 | V91: 10 | W91: N | X91: entering head-on = fighting free incumbents; differentiation must come from bundle/ecosystem (e.g. curl → replayable request bin link). | Y91: Converting curl commands (copied from docs/DevTools) into Python/JS/PHP code is a standing need — proven by an entire category of converter sites.
B92: 88 | C92: EC-C23 | D92: Chasing unpaid invoices is socially awkward and un-systematized for freelancers: "I usually give a week's g... | E92: E-commerce & SMB | F92: E-commerce & SMB Ops | G92: E1 | H92: 6.55 | I92: 7 | J92: 7 | K92: 5 | L92: 8.5 | M92: 6 | N92: 7 | O92: 3.5 | P92: 6 | Q92: 7 | R92: 4 | S92: GLUE | T92: FREE | U92: 12 | V92: 10 | W92: N | Y92: Chasing unpaid invoices is socially awkward and un-systematized for freelancers: "I usually give a week's grace… then start contacting every day"; automated escalating reminders are the stated fix.
B93: 89 | C93: GT-JSON-json-DV-B20 | D93: JSON Escape / Unescape | E93: DevTools & Data | F93: Developer Tools | G93: E3 | H93: 6.55 | I93: 6 | J93: 5 | K93: 7 | L93: 10 | M93: 4 | N93: 8 | O93: 5 | P93: 10 | Q93: 6 | R93: 3 | S93: GLUE | T93: FREE | U93: 5 | V93: 10 | W93: N | X93: json escape online | Y93: Long-tail tool instance: JSON Escape / Unescape. Pattern-inherited pain evidence from DV-B20 cluster; ships as part of the mega-toolbox catalog (<=1 use/month tools included by directive).
B94: 90 | C94: GT-CSV-csv-DR-B1 | D94: CSV to SQL INSERT Generator | E94: Data & Repair | F94: Data & File Repair | G94: E3 | H94: 6.55 | I94: 6 | J94: 5 | K94: 5 | L94: 10 | M94: 5 | N94: 8 | O94: 5 | P94: 10 | Q94: 7 | R94: 4 | S94: GLUE | T94: FREE | U94: 10 | V94: 10 | W94: N | X94: csv to sql insert | Y94: Long-tail tool instance: CSV to SQL INSERT Generator. Pattern-inherited pain evidence from DR-B1 cluster; ships as part of the mega-toolbox catalog (<=1 use/month tools included by directive).
B95: 91 | C95: GT-SUB-srt-DR-S1 | D95: SRT to VTT Converter | E95: Data & Repair | F95: Data & File Repair | G95: E3 | H95: 6.55 | I95: 6 | J95: 6 | K95: 4 | L95: 10 | M95: 4 | N95: 9 | O95: 4 | P95: 10 | Q95: 7 | R95: 4 | S95: GLUE | T95: FREE | U95: 5 | V95: 10 | W95: N | X95: srt to vtt converter | Y95: Long-tail tool instance: SRT to VTT Converter. Pattern-inherited pain evidence from DR-S1 cluster; ships as part of the mega-toolbox catalog (<=1 use/month tools included by directive).
B96: 92 | C96: GT-SQL-sql-DV-B10 | D96: SQL Formatter / Beautifier | E96: DevTools & Data | F96: Developer Tools | G96: E3 | H96: 6.55 | I96: 7 | J96: 4 | K96: 7 | L96: 10 | M96: 3 | N96: 9 | O96: 4 | P96: 10 | Q96: 6 | R96: 3 | S96: HOOK | T96: FREE | U96: 10 | V96: 10 | W96: N | X96: sql formatter online | Y96: Long-tail tool instance: SQL Formatter / Beautifier. Pattern-inherited pain evidence from DV-B10 cluster; ships as part of the mega-toolbox catalog (<=1 use/month tools included by directive).
B97: 93 | C97: DV-B15 | D97: Unix timestamp/timezone conversion errors — devs repeatedly confuse epoch vs local time, DST edges, and lan... | E97: DevTools & Data | F97: Developer Tools | G97: E2 | H97: 6.53 | I97: 8.5 | J97: 5 | K97: 7 | L97: 10 | M97: 5 | N97: 3.5 | O97: 1 | P97: 7.5 | Q97: 8 | R97: 4 | S97: GLUE | T97: FREE | U97: 10 | V97: 10 | W97: N | X97: batch timestamp→human-readable converter + timezone-aware cron preview = ecosystem glue. | Y97: Unix timestamp/timezone conversion errors — devs repeatedly confuse epoch vs local time, DST edges, and language-specific parsing (TZ env pitfalls).
B98: 94 | C98: DV-B4 | D98: Cryptic API error responses cost hours — teams build tribal knowledge around undocumented 4xx/5xx bodies. | E98: DevTools & Data | F98: Developer Tools | G98: E1 | H98: 6.5 | I98: 8 | J98: 7 | K98: 7 | L98: 5.5 | M98: 2.5 | N98: 8.5 | O98: 8 | P98: 6 | Q98: 8 | R98: 2.5 | S98: HOOK | T98: FREE | U98: 52 | V98: 45 | W98: Y | X98: pairs naturally with AI gateway (B-row feeds router usage). | Y98: Cryptic API error responses cost hours — teams build tribal knowledge around undocumented 4xx/5xx bodies.
B99: 95 | C99: GT-FIN-convert-DR-D1 | D99: OFX / QBO to CSV Converter | E99: Data & Repair | F99: Data & File Repair | G99: E3 | H99: 6.5 | I99: 5 | J99: 7 | K99: 3 | L99: 9 | M99: 7 | N99: 8 | O99: 6 | P99: 8 | Q99: 7 | R99: 5 | S99: LTV | T99: PRO | U99: 30 | V99: 10 | W99: N | X99: convert qbo to csv | Y99: Long-tail tool instance: OFX / QBO to CSV Converter. Pattern-inherited pain evidence from DR-D1 cluster; ships as part of the mega-toolbox catalog (<=1 use/month tools included by directive).
B100: 96 | C100: GT-SQL-convert-DV-B15 | D100: Epoch / ISO / Timezone Batch Converter | E100: DevTools & Data | F100: Developer Tools | G100: E3 | H100: 6.5 | I100: 6 | J100: 5 | K100: 5 | L100: 10 | M100: 4 | N100: 9 | O100: 5 | P100: 10 | Q100: 7 | R100: 3 | S100: GLUE | T100: FREE | U100: 8 | V100: 10 | W100: N | X100: convert epoch batch | Y100: Long-tail tool instance: Epoch / ISO / Timezone Batch Converter. Pattern-inherited pain evidence from DV-B15 cluster; ships as part of the mega-toolbox catalog (<=1 use/month tools included by directive).
B101: 97 | C101: GT-CFG-yaml-DV-B19 | D101: YAML to JSON to TOML Converter | E101: DevTools & Data | F101: Developer Tools | G101: E3 | H101: 6.5 | I101: 6 | J101: 5 | K101: 5 | L101: 10 | M101: 4 | N101: 9 | O101: 5 | P101: 10 | Q101: 7 | R101: 3 | S101: HOOK | T101: FREE | U101: 14 | V101: 10 | W101: N | X101: yaml to json toml converter | Y101: Long-tail tool instance: YAML to JSON to TOML Converter. Pattern-inherited pain evidence from DV-B19 cluster; ships as part of the mega-toolbox catalog (<=1 use/month tools included by directive).
B102: 98 | C102: GT-SEC-base64-DV-B20 | D102: Base64 Encoder / Decoder (+files) | E102: Web & Text Utilities | F102: Web & Text Utilities | G102: E3 | H102: 6.5 | I102: 8 | J102: 4 | K102: 6 | L102: 10 | M102: 3 | N102: 9 | O102: 3 | P102: 10 | Q102: 5 | R102: 2 | S102: HOOK | T102: FREE | U102: 6 | V102: 10 | W102: N | X102: base64 encode online | Y102: Long-tail tool instance: Base64 Encoder / Decoder (+files). Pattern-inherited pain evidence from DV-B20 cluster; ships as part of the mega-toolbox catalog (<=1 use/month tools included by directive).
...

Sheet Top 50
B2: Top 50 Opportunities by Composite Score
B4: Rank | C4: ID | D4: Tool / Opportunity | E4: Zone | F4: Score | G4: Role | H4: Tier | I4: Why it wins (abridged) | J4: Existing tools / price anchors | K4: Src URLs
B5: 1 | C5: DR-C3 | D5: Adobe Acrobat's subscription-only pricing outrages buyers who need occasional PDF editing/merging/forms. | E5: Data & Repair | F5: 8.2 | G5: HOOK | H5: FREE | I5: Adobe Acrobat's subscription-only pricing outrages buyers who need occasional PDF editing/merging/forms. | J5: iLovePDF (free tier w/ file-size caps; Premium $5/mo annual, $9/mo monthly — ilovepdf.com/pricing), Smallpdf (free 2 tasks/day-ish trial behavior; Pro $12/mo or $108/yr — ihatepdf comparison + smallpdf pricing page), PDF | K5: 4
B6: 2 | C6: DR-F1 | D6: Bookkeepers cannot import bank transactions from PDF statements — QuickBooks Online users beg for PDF→CSV/Q... | E6: Data & Repair | F6: 8.03 | G6: LTV | H6: PRO | I6: Bookkeepers cannot import bank transactions from PDF statements — QuickBooks Online users beg for PDF→CSV/QBO conversion and are desperate when banks close online history. | J6: DocuClipper (from $39.95-$49.95/mo for 20 conversions per docuclipper blog — verified on their blog), MoneyThumb 2qbo Convert Pro+ ($299.95 — capyparse review), ProperSoft ProperConvert (desktop, one-time, price on purch | K6: 3
B7: 3 | C7: GT-PDF-extract-DR-C2 | D7: PDF Table Extractor to CSV (text-layer) | E7: Data & Repair | F7: 7.75 | G7: LTV | H7: PRO | I7: Long-tail tool instance: PDF Table Extractor to CSV (text-layer). Pattern-inherited pain evidence from DR-C2 cluster; ships as part of the mega-toolbox catalog (<=1 use/month tools included by directive). | J7: Inherits demand pattern from research row DR-C2 (see DR-C2 for E1/E2 evidence). | K7: 0
B8: 4 | C8: DR-D2 | D8: One conversion job requires stitching 3-5 different single-purpose sites/tools; users lose track and hit ea... | E8: Data & Repair | F8: 7.67 | G8: HOOK | H8: FREE | I8: One conversion job requires stitching 3-5 different single-purpose sites/tools; users lose track and hit each tool's free caps. | J8: iLovePDF (free caps, Premium $5/mo annual per pricing page), Smallpdf (Pro $12/mo, $108/yr), Adobe online. | K8: 4
B9: 5 | C9: DR-B2 | D9: Multi-hundred-MB/GB JSON & JSONL files crash or freeze editors (VS Code 5MB JSON mode limit; 700MB jsonline... | E9: Data & Repair | F9: 7.62 | G9: HOOK | H9: FREE | I9: Multi-hundred-MB/GB JSON & JSONL files crash or freeze editors (VS Code 5MB JSON mode limit; 700MB jsonlines crashes VS Code). | J9: Dadroit (free viewer, commercial product), Janice (free desktop), jq (free CLI). | K9: 3
B10: 6 | C10: DR-H1 | D10: SMBs and individuals still spend hours monthly on manual invoice/receipt data entry and want any automation... | E10: Data & Repair | F10: 7.6 | G10: LTV | H10: MAX | I10: SMBs and individuals still spend hours monthly on manual invoice/receipt data entry and want any automation that actually works. | J10: Expensify (freemium, price unverified), Dext (paid, unverified), DIY OCR scripts. | K10: 4
B11: 7 | C11: WG-G4 | D11: Hallucinated citations — verifying AI-generated references | E11: Education & Weird Gold | F11: 7.6 | G11: LTV | H11: MAX | I11: Nature-linked analysis: "Tens of thousands of publications from 2025 might include invalid references generated by AI" (r/technology thread: https://www.reddit.com/r/technology/comments/1sd0khs/); study: ChatGPT false-citation rates 6%–60% by domain (https://www.psypost.org/chatgpt-hallucinates-fake | J11: Sourcely et al. push paid "verify sources" SaaS (https://www.sourcely.net/resources/ai-hallucinated-citations-spot-fake-sources-before-submit); no dominant free batch-verifier found in results. | K11: 6
B12: 8 | C12: GT-CSV-split-DR-B2 | D12: CSV Splitter (rows / file size) | E12: Data & Repair | F12: 7.6 | G12: PRO | H12: PRO | I12: Long-tail tool instance: CSV Splitter (rows / file size). Pattern-inherited pain evidence from DR-B2 cluster; ships as part of the mega-toolbox catalog (<=1 use/month tools included by directive). | J12: Inherits demand pattern from research row DR-B2 (see DR-B2 for E1/E2 evidence). | K12: 0
B13: 9 | C13: GT-CSV-excel-DR-A2 | D13: Leading-Zero & Date Guard (CSV open protector) | E13: Data & Repair | F13: 7.6 | G13: PRO | H13: PRO | I13: Long-tail tool instance: Leading-Zero & Date Guard (CSV open protector). Pattern-inherited pain evidence from DR-A2 cluster; ships as part of the mega-toolbox catalog (<=1 use/month tools included by directive). | J13: Inherits demand pattern from research row DR-A2 (see DR-A2 for E1/E2 evidence). | K13: 0
B14: 10 | C14: EC-C21 | D14: Manually matching bank/UPI payments to invoices/orders — sellers literally work out "which combinations of ... | E14: E-commerce & SMB | F14: 7.58 | G14: LTV | H14: PRO | I14: Manually matching bank/UPI payments to invoices/orders — sellers literally work out "which combinations of invoice amounts add up to each payment amount" on weekends; UPI/direct-transfer payments arrive with no references. | J14: accounting suites assume bank-feed auto-match (needs QBO/Xero + connected bank — unavailable for UPI/BD bank setups). | K14: 3
B15: 11 | C15: DV-B1 | D15: JSON viewers/editors crash or freeze on large (100MB–1GB+) JSON files, so devs fall back to command-line jq... | E15: DevTools & Data | F15: 7.58 | G15: PRO | H15: PRO | I15: JSON viewers/editors crash or freeze on large (100MB–1GB+) JSON files, so devs fall back to command-line jq or buy specialized viewers. | J15: Dadroit (commercial, price unverified), UltraEdit, jq (free CLI). | K15: 2
B16: 12 | C16: DR-A2 | D16: CSVs open with all data in one column or split wrongly because the delimiter is comma vs semicolon (Europea... | E16: Data & Repair | F16: 7.55 | G16: HOOK | H16: FREE | I16: CSVs open with all data in one column or split wrongly because the delimiter is comma vs semicolon (European locale) or SEP= line missing. | J16: Excel wizard, LibreOffice (free), many delimiter-converter web tools (unverified). | K16: 2
... B54: 50 | C54: EC-C15 | D54: Google Merchant Center disapprovals spike suddenly and in bulk: price-mismatch, missing GTIN, misclassified... | E54: E-commerce & SMB | F54: 7.03 | G54: LTV | H54: PRO | I54: Google Merchant Center disapprovals spike suddenly and in bulk: price-mismatch, missing GTIN, misclassified policy flags (e.g., 530 products flagged "Alcoholic drinks" wrongly); fixes require per-attribute edits across the feed. | J54: DataFeedWatch from ~$59–64/mo (F6); feed tools price out micro-sellers. | K54: 5

Sheet Clusters
B2: Zone-Level Portfolio Statistics
B4: Zone | C4: Tools | D4: Avg score | E4: Max score | F4: LTV | G4: PRO | H4: HOOK | I4: GLUE | J4: E1 rows | K4: E2 rows | L4: Build effort h | M4: Maint min/wk
B5: Data & Repair | C5: 60 | D5: 6.87 | E5: 8.2 | F5: 10 | G5: 18 | H5: 15 | I5: 17 | J5: 26 | K5: 1 | L5: 946 | M5: 845
B6: E-commerce & SMB | C6: 52 | D6: 6.44 | E6: 7.58 | F6: 14 | G6: 19 | H6: 2 | I6: 17 | J6: 30 | K6: 1 | L6: 858 | M6: 710
B7: DevTools & Data | C7: 55 | D7: 6.23 | E7: 7.58 | F7: 3 | G7: 11 | H7: 14 | I7: 27 | J7: 9 | K7: 7 | L7: 837 | M7: 805
B8: BD & Telegram | C8: 4 | D8: 6.09 | E8: 6.9 | F8: 2 | G8: 1 | H8: 0 | I8: 1 | J8: 0 | K8: 0 | L8: 133 | M8: 100
B9: Education & Weird Gold | C9: 48 | D9: 5.94 | E9: 7.6 | F9: 3 | G9: 14 | H9: 7 | I9: 24 | J9: 14 | K9: 6 | L9: 1488 | M9: 1355
B10: Media & Image | C10: 7 | D10: 5.87 | E10: 6.75 | F10: 0 | G10: 1 | H10: 4 | I10: 2 | J10: 0 | K10: 0 | L10: 102 | M10: 70
B11: Web & Text Utilities | C11: 21 | D11: 5.77 | E11: 6.6 | F11: 0 | G11: 1 | H11: 11 | I11: 9 | J11: 0 | K11: 0 | L11: 128 | M11: 210
B12: TOTAL | C12: 247 | D12: 6.32 | E12: 8.2 | F12: 32 | G12: 65 | H12: 53 | I12: 97 | J12: 79 | K12: 15 | L12: 4492 | M12: 4095
B14: Avg score column = mean composite per zone. Build effort = cumulative one-time build hours estimate (maint min/wk = recurring). Zones ordered by average score.

Sheet Pricing Model
B2: Subscription Model — One Product, Many Tools (anti-underpricing)
B4: Tier | C4: Price | D4: Annual | E4: Who it serves | F4: Limits & unlockables | G4: Platform roles served | H4: Value anchor (what it replaces) | I4: Why price is fair
B5: FREE | C5: $0 | D5: $0 | E5: Anyone arriving from search; students; casual one-off users | F5: All client-side tools unlimited; server/AI tools metered daily (10 credits); watermark/credit on shareable outputs; 1 concurrent job | G5: HOOK (53) + GLUE core (97) | H5: free alternatives: iLovePDF free, crontab.guru, jwt.io | I5: Free tier is the SEO engine: every tool page = a landing page; converts via caps + batch needs
B6: PRO | C6: $4.99/mo | D6: $39/yr | E6: Sellers, freelancers, students, office workers (the 95% case) | F6: Full 240+ toolbox; batch mode; no watermarks; 300 server credits/mo; 2GB files; priority queue | G6: PRO (65) + heavy GLUE | H6: iLovePDF ~$4-7/mo for PDF-only; Smallpdf $9/mo; Matrixify $20/mo for Shopify-only | I6: One niche incumbent charges more than PRO for ONE domain; FRAZIYM covers data+PDF+e-com+dev in one
B7: STUDIO | C7: $9.99/mo | D7: $79/yr | E7: Power users: accountants, agencies, AI-native devs | F7: PRO + AI-featured tools (1,500 AI credits/mo): citation verifier, error decoder, quiz/show-notes gen; API-lite 1k calls/mo; Telegram Mini App perks | G7: LTV (32) AI-assisted | H7: DocuClipper $49.95/mo (bank stmt only); Dext $13-20.50/mo (receipts only); DataFeedWatch $59/mo (feeds only) | I7: STUDIO replaces any ONE niche subscription at <25% of its price while including everything else
B8: MAX | C8: $19.99/mo | D8: $159/yr | E8: Small teams (3 seats), integrators, automation-heavy users | F8: STUDIO x3 seats + 5,000 AI credits + webhook workspace (bins/replay) + MCP tooling + 25k API calls + priority support | G8: LTV server-side + teams | H8: Postman $14/user/mo (1 user!); Hookdeck from ~$19/mo; ngrok $8-10/mo | I8: 3-seat team plan beats Postman single-user price; metered server features protected by caps
B10: Profit mechanics
B12: Infra cost | C12: $0 | D12: Cloudflare free tier (Workers 100k req/day, Pages, D1, R2, Queues, Cron) — verified 2026-09-02
B13: AI cost | C13: $0 | D13: Multi-provider free gateway: Groq + OpenRouter:free + CF Workers AI + SambaNova + Mistral ≈ 500-2,000 req/day pooled; cache-first routing
B14: Payment fees | C14: ~2-5% | D14: USDT P2P->bKash ≈1.4-2% (cheapest); Telegram Stars ≈4-5% (21-day hold); Paddle 5%+$1 when scale requires
B15: Gross margin | C15: ≈95-98% | D15: Revenue minus payment fees only; no hosting/AI fixed cost under free caps
B16: Underpricing guard | C16: Rule | D16: Any tier price change must stay above: (a) 2x cheapest single-niche competitor monthly price ÷ 20, (b) willingness-to-pay evidence floor $4/mo; never compete to $0
B18: Prices in USD. Stars/crypto rails avoid the Stripe/PayPal wall for a Bangladesh solo founder (see Payment Rails sheet). Prices intentionally at market-mid of consumer utility SaaS, not race-to-bottom.

Sheet Revenue Scenarios
B2: Revenue Scenarios — subscriber math (fees net of infra $0)
B4: Tier price assumptions (editable)
B6: PRO $/mo | C6: 4.99
B7: STUDIO $/mo | C7: 9.99
B8: MAX $/mo | C8: 19.99
B9: Ads+affiliate $/day (conservative) | C9: 0
B11: Scenarios (live formulas)
B12: Scenario | C12: PRO subs | D12: STUDIO subs | E12: MAX subs | F12: MRR $ | G12: $/day | H12: Fees ~% | I12: Net $/day | J12: Funnel assumption (E3) | K12: Trigger date (90-day plan) | L12: Cumulative tools live
B13: A — First blood | C13: 1 | D13: 0 | E13: 0 | F13: =C13*C6+D13*C7+E13*C8 -> 4.99 | G13: =F13*12/365 -> 0.16405479 | H13: 2 | I13: =G13*(1-H13/100)+C9 -> 0.1607737 | J13: Day 21-45: first paid conversion from one seeded tool's thank-you page | K13: Day 30: 6 tools | L13: 6
B14: B — $1/day | C14: 3 | D14: 1 | E14: 0 | F14: =C14*C6+D14*C7+E14*C8 -> 24.96 | G14: =F14*12/365 -> 0.82060274 | H14: 2.5 | I14: =G14*(1-H14/100)+C9 -> 0.80008767 | J14: 400-800 free-tool visits/day converting 0.5-1% to paid | K14: Day 45: 12 tools | L14: 12
B15: C — $3/day | C15: 8 | D15: 3 | E15: 1 | F15: =C15*C6+D15*C7+E15*C8 -> 89.88 | G15: =F15*12/365 -> 2.9549589 | H15: 3 | I15: =G15*(1-H15/100)+C9 -> 2.8663101 | J15: 1.5-3k visits/day via pSEO long-tail + Telegram channel | K15: Day 60: 25 tools | L15: 25
B16: D — $10/day | C16: 25 | D16: 8 | E16: 3 | F16: =C16*C6+D16*C7+E16*C8 -> 264.64 | G16: =F16*12/365 -> 8.7004932 | H16: 4 | I16: =G16*(1-H16/100)+C9 -> 8.3524734 | J16: 6-10k visits/day; churn <8%/mo; 2-4% free->paid on segment-fit tools | K16: Day 90: 45 tools | L16: 45
B17: E — $30/day | C17: 70 | D17: 25 | E17: 8 | F17: =C17*C6+D17*C7+E17*C8 -> 758.97 | G17: =F17*12/365 -> 24.952438 | H17: 5 | I17: =G17*(1-H17/100)+C9 -> 23.704816 | J17: 15-25k visits/day; email/Telegram list 5-10k; affiliate + AdsGram adds ~$7/day | K17: Month 5-6: 80+ tools | L17: 80
B19: MRR and $/day are live formulas — edit tier prices above to re-model. Fees = blended payment-rail cost (see Payment Rails). Scenario D/E assume affiliate + AdsGram top-ups beyond subscriptions (entered conservatively at $0 here; PDF report shows with +$1.5-7/day). Free->paid conversion assumptions are E3 and must be validated with real funnel data. Note: '工具-fit' = segment fit.

Sheet Payment Rails
B2: Payout Rails for BD Solo Founder (no bank/card) — verified 2026-09-02
B4: Rail | C4: Verdict | D4: Fees | E4: Min payout | F4: KYC | G4: Timeline | H4: Notes / risk | I4: Confidence
B5: Crypto affiliate USDT -> P2P -> bKash (Bybit/OKX) | C5: WORKS — cheapest chain | D5: ~1.4-2% total | E5: exchange min | F5: Exchange KYC + P2P counterparty | G5: hours-1 day | H5: Prefer Bybit/OKX P2P (0% fee, bKash/Nagad listed); Binance BD restricted Mar 2025; USDT/BDT rate 122-124 = +2-3.5% FX bonus; risk = MFS wallet freezes from many small P2P credits | I5: High (E2)
B6: Telegram Stars -> Fragment -> GRAM -> USDT -> P2P | C6: WORKS — native for TG products | D6: ~4-5% total | E6: 1,000 Stars (~$13) | F6: Fragment KYC mandatory (purchases since Nov 2024) | G6: 21-day hold + payout | H6: $0.013/Star payout rate; Toncoin renamed GRAM 1:1 (Jun 15, 2026) | I6: High (E2)
B7: AdsGram (TGA mini-app ads) | C7: WORKS — official TG ad network | D7: net-45 style | E7: $100 | F7: light | G7: monthly | H7: USDT-TON payouts; rewarded ads in Mini Apps | I7: Med-High (E2)
B8: Adsterra | C8: WORKS (crypto) | D8: rev-share | E8: $100 crypto (USDT-TRC20) | F8: email | G8: net-14/16 | H8: The famous $5 min is WebMoney/Paxum only, NOT crypto | I8: High (E2)
B9: Paddle -> Payoneer -> bKash | C9: WORKS — only mainstream SaaS checkout open to BD | D9: 3% + $1 (Payoneer->bKash min BDT 1000, cap BDT 250k/tx) | E9: Paddle $1,000 initial review bar | F9: Payoneer KYC (BD ID ok) | G9: weekly/2x-monthly | H9: Merchant-of-record solves sales tax; use when subscription volume justifies | I9: Med-High (E2)
B10: NOWPayments / BTCPay (accept rails) | C10: WORKS — inbound crypto acceptance | D10: 0.5-1.5% / 0% (self-host BTC-only) | E10: none-material | F10: email | G10: instant | H10: Accept USDT/BTC from customers; pair with P2P off-ramp | I10: Med (E2)
B11: Direct MTO remittance -> bKash (WU/MoneyGram/ACE/Taptap) | C11: WORKS but compliance-grey for client fees | D11: ~0.7% ATM cash-out; +2.5% govt incentive on remittance | E11: low | F11: ID per transfer | G11: minutes-hours | H11: Cheapest per-dollar; grey area for commercial receipts (FERA) — use for personal withdrawals, not client invoicing | I11: Med (E2/E3)
B12: Google AdSense | C12: BROKEN | D12: - | E12: $100 | F12: - | G12: - | H12: BD = wire-to-bank only; WU Quick Cash dead | I12: High (E2)
B13: Stripe / PayPal / Gumroad / Ko-fi / BMC / Patreon / Payhip / LemonSqueezy | C13: BROKEN | D13: - | E13: - | F13: - | G13: - | H13: All require BD bank or Stripe/PayPal payout country | I13: High (E2)
B14: Telegram channel ads rev-share (>=1k subs, 50%) | C14: UNVERIFIED for BD | D14: 50% share | E14: - | F14: - | G14: - | H14: Check in-app toggle; AdsGram is the fallback | I14: Low (E3)
B15: Bangladesh Bank legal note | C15: CONSTRAINT | D15: - | E15: - | F15: - | G15: - | H15: Crypto = grey zone (FERA 1947); practical risk = MFS freezes, not prosecution; keep P2P credits small & irregular | I15: Med (E2/E3)
B17: Full ledger with sources: research/payments.md. Strategy: start Stars + crypto (zero-setup), graduate to Paddle->Payoneer at scale for card-paying customers.

Sheet Free Infra
B2: $0 Infrastructure Stack — verified limits 2026-09-02
B4: Service | C4: Free-tier allowance | D4: Hard gotcha | E4: Role in FRAZIYM
B5: Cloudflare Workers | C5: 100k req/day, 10ms CPU | D5: CPU-time cap kills heavy compute; offload to client WASM | E5: API gateway + router + bots
B6: Cloudflare Pages | C6: unlimited bandwidth, 500 builds/mo | D6: — | E6: all static tool frontends
B7: Cloudflare D1 | C7: 5M reads/day, 100k writes/day, 5GB | D7: writes capped — batch/analytics offload | E7: users, usage ledger, tool registry
B8: Cloudflare R2 | C8: 10GB storage, 1M A/10M B ops, $0 egress | D8: — | E8: file staging for server-side jobs
B9: Cloudflare Queues + Cron | C9: Queues 10k ops/day (Feb 2026 change); Cron reliable | D9: — | E9: async jobs + schedulers
B10: Cloudflare KV | C10: 1k writes/day | D10: low-write only | E10: config/cache
B11: Turso / Neon | C11: Turso 500M reads/10M writes/5GB; Neon 100 CU-hr + 5-min autosuspend | D11: Neon autosuspend = cold starts; heartbeat cron mandatory | E11: DB depth beyond D1
B12: Supabase | C12: 2 projects, 500MB | D12: PAUSES after 7 days idle | E12: avoid as primary
B13: GitHub | C13: Actions 2,000 min/mo private (unlimited public); scheduled workflows BEST-EFFORT (60-day disable) | D13: never rely on GH cron for revenue jobs | E13: CI, OSS repo trust, Pages mirror
B14: Vercel Hobby | C14: 100GB, 1M invocations | D14: NON-COMMERCIAL terms; cron max 1/day | E14: avoid for the product itself
B15: Netlify | C15: 300 credits (~15GB) hard cap | D15: downgraded free tier | E15: dropped from stack
... B21: Domains | C21: DigitalPlat free (.dpdns.org/.us.kg); .xyz/.top $1-2 yr-1 | D21: custom domain REQUIRED for email/OAuth trust | E21: root domain + API subdomain
B23: Full 16-section verification with sources: research/infra.md. Architecture rule: anchor on Cloudflare; treat every free tier as disposable (failover-ready).

Sheet AI Providers
B2: Free AI Inference Providers — gateway design inputs 2026-09-02
B4: Provider | C4: Free allowance (verified) | D4: Card needed | E4: ToS / data notes | F4: Role in router
B5: Groq | C5: 30 RPM / 1K RPD / 8K TPM (gpt-oss + qwen); Whisper 2K RPD & 28.8k audio-sec/day | D5: No | E5: cached tokens excluded from limits | F5: PRIMARY anchor (speed + STT)
B6: OpenRouter :free | C6: 20 RPM, 50 RPD (1,000 RPD after $10 credit purchase) | D6: No | E6: free models = data-training pool | F6: SECONDARY + model variety
B7: Cloudflare Workers AI | C7: 10,000 Neurons/day | D7: No | E7: same stack as product = one bill, zero | F7: TERTIARY + embedding/small tasks
B8: SambaNova | C8: 20 RPM / 20 RPD / 200K TPD | D8: No | E8: — | F8: failover
B9: Mistral La Plateforme | C9: free tier exists (rate-limited) | D9: Phone verify | E9: — | F9: failover
B10: Cohere | C10: trial 1,000 calls/mo @20 RPM | D10: No | E10: trial key only | F10: embed/rank niche
B11: Gemini (AI Studio) | C11: free tier exists but ~20 RPD (Dec 2025 slash; no public table) | D11: No | E11: DATA USED FOR TRAINING = YES | F11: last-resort only
B12: Hugging Face Inference | C12: ~$0.10/mo free credits | D12: No | E12: — | F12: drop from router
B13: Cerebras / Together / GitHub Models | C13: ALL free tiers RETIRED (2025-07/2026-02/2026-07) | D13: - | E13: — | F13: removed
B14: Local (llama.cpp on Termux) | C14: 0-cost, device-bound | D14: - | E14: — | F14: offline dev-time fallback only
B16: Router policy: validate -> deterministic first -> cache -> small/local model -> free-cloud failover -> validate again. Pooled capacity ≈ 500-2,000 AI req/day at $0. Single account per provider (multi-accounting prohibited). Sources: research/ai-providers.md.

Sheet Review
B2: Cross-Validation (live checks)
B4: Check | C4: Expected | D4: Actual | E4: Status
B5: Opportunities row count | C5: 247 | D5: =COUNTA(Opportunities!C5:C251) -> 247 | E5: =IF(ROUND(C5,2)=ROUND(D5,2),"PASS","FAIL") -> PASS
B6: Top 50 row count | C6: 50 | D6: =COUNTA('Top 50'!C5:C54) -> 50 | E6: =IF(ROUND(C6,2)=ROUND(D6,2),"PASS","FAIL") -> PASS
B7: Clusters tool sum | C7: 247 | D7: =Clusters!C12 -> 247 | E7: =IF(ROUND(C7,2)=ROUND(D7,2),"PASS","FAIL") -> PASS
B8: Scenario B MRR ($) | C8: 24.96 | D8: ='Revenue Scenarios'!F14 -> 24.96 | E8: =IF(ROUND(C8,2)=ROUND(D8,2),"PASS","FAIL") -> PASS
B9: LTV+PRO+HOOK+GLUE sum | C9: 247 | D9: =COUNTIF(Opportunities!S5:S251,"LTV")+COUNTIF(Opportunities!S5:S251,"PRO")+COUNTIF(Opportunities!S5:S251,"HOOK")+COUNTIF(Opportunities!S5:S251,"GLUE") -> 247 | E9: =IF(ROUND(C9,2)=ROUND(D9,2),"PASS","FAIL") -> PASS
